baml_lib-0.42.0.dist-info/METADATA
baml_lib-0.42.0.dist-info/WHEEL
baml_lib/__init__.py
baml_lib/baml_lib.cpython-39-x86_64-linux-gnu.so
baml_lib-0.42.0.dist-info/RECORD
