Metadata-Version: 2.4
Name: baml_lib
Version: 0.42.0
Summary: BAML Library for Python
Keywords: baml,llm
Author: hhclaw
Author-email: Boundary <contact@boundaryml.com>
Project-URL: Homepage, https://github.com/hhclaw/baml-lib
Project-URL: Repository, https://github.com/hhclaw/baml-lib
Project-URL: Issues, https://github.com/hhclaw/baml-lib/issues
